{"nodes": [{"id": "c_users_kheff_kaiylo_project_frontend_src_components_sortcontrol_jsx", "label": "SortControl.jsx", "file_type": "code", "source_file": "C:\\Users\\kheff\\Kaiylo_Project\\frontend\\src\\components\\SortControl.jsx", "source_location": "L1"}, {"id": "components_sortcontrol_sortcontrol", "label": "SortControl()", "file_type": "code", "source_file": "C:\\Users\\kheff\\Kaiylo_Project\\frontend\\src\\components\\SortControl.jsx", "source_location": "L12"}], "edges": [{"source": "c_users_kheff_kaiylo_project_frontend_src_components_sortcontrol_jsx", "target": "react", "relation": "imports_from", "confidence": "EXTRACTED", "source_file": "C:\\Users\\kheff\\Kaiylo_Project\\frontend\\src\\components\\SortControl.jsx", "source_location": "L1", "weight": 1.0}, {"source": "c_users_kheff_kaiylo_project_frontend_src_components_sortcontrol_jsx", "target": "c_users_kheff_kaiylo_project_frontend_src_components_ui_dropdown_menu", "relation": "imports_from", "confidence": "EXTRACTED", "source_file": "C:\\Users\\kheff\\Kaiylo_Project\\frontend\\src\\components\\SortControl.jsx", "source_location": "L2", "weight": 1.0}, {"source": "c_users_kheff_kaiylo_project_frontend_src_components_sortcontrol_jsx", "target": "lucide_react", "relation": "imports_from", "confidence": "EXTRACTED", "source_file": "C:\\Users\\kheff\\Kaiylo_Project\\frontend\\src\\components\\SortControl.jsx", "source_location": "L10", "weight": 1.0}, {"source": "c_users_kheff_kaiylo_project_frontend_src_components_sortcontrol_jsx", "target": "components_sortcontrol_sortcontrol", "relation": "contains", "confidence": "EXTRACTED", "source_file": "C:\\Users\\kheff\\Kaiylo_Project\\frontend\\src\\components\\SortControl.jsx", "source_location": "L12", "weight": 1.0}], "raw_calls": [{"caller_nid": "components_sortcontrol_sortcontrol", "callee": "useState", "source_file": "C:\\Users\\kheff\\Kaiylo_Project\\frontend\\src\\components\\SortControl.jsx", "source_location": "L13"}, {"caller_nid": "components_sortcontrol_sortcontrol", "callee": "find", "source_file": "C:\\Users\\kheff\\Kaiylo_Project\\frontend\\src\\components\\SortControl.jsx", "source_location": "L25"}, {"caller_nid": "components_sortcontrol_sortcontrol", "callee": "getOptionValue", "source_file": "C:\\Users\\kheff\\Kaiylo_Project\\frontend\\src\\components\\SortControl.jsx", "source_location": "L39"}, {"caller_nid": "components_sortcontrol_sortcontrol", "callee": "map", "source_file": "C:\\Users\\kheff\\Kaiylo_Project\\frontend\\src\\components\\SortControl.jsx", "source_location": "L90"}]}